LICENSE
README.md
setup.py
tests/test_bert.py
tests/test_falcon.py
tests/test_functions.py
tests/test_modules.py
tests/test_resnet.py
tests/test_vit.py
torchtrail/__init__.py
torchtrail/tracer.py
torchtrail.egg-info/PKG-INFO
torchtrail.egg-info/SOURCES.txt
torchtrail.egg-info/dependency_links.txt
torchtrail.egg-info/requires.txt
torchtrail.egg-info/top_level.txt