Metadata-Version: 2.1
Name: torchtrail
Version: 0.0.19
Summary: A library for tracing the execution of Pytorch operations and modules
Home-page: https://github.com/arakhmati/torchtrail
Author: Akhmed Rakhmati
Author-email: akhmed.rakhmati@gmail.com
Keywords: pytorch,tracing,tracing library,tracing tool,tracing module,tracing operations,visualize,visualize pytorch,visualize pytorch operations,visualize pytorch modules
Provides-Extra: dev
License-File: LICENSE
